{
  "heroes": [
    {
      "id": 1,
      "name": "Первый герой",
      "description": "Первый герой в рейтинге!",
      "element": "fire"
    },
    {
      "id": 2,
      "name": "Неизвестный герой",
      "description": "Скрывающийся в тени",
      "element": "wind"
    },
    {
      "id": 3,
      "name": "Морской герой",
      "description": "Как аквамен, но не из DC",
      "element": "water"
    },
    {
      "name": "Головкин Олег Евгеньевич",
      "distription": "Вода",
      "element": "",
      "id": 4
    },
    {
      "name": "Головкин",
      "distription": "Олег",
      "element": "Вода",
      "id": 5
    },
    {
      "name": "dadssad",
      "distription": "Головкни",
      "element": "Огонь",
      "id": 6
    },
    {
      "name": "вывыв",
      "distription": "dsdasd",
      "element": "Вода",
      "id": 7
    },
    {
      "name": "аыва",
      "distription": "вфыв",
      "element": "Вода",
      "id": 8
    },
    {
      "name": "вфыв",
      "distription": "вфыв",
      "element": "Вода",
      "id": 9
    },
    {
      "name": "аыва",
      "distription": "мчмчс",
      "element": "Все",
      "id": 10
    }
  ],
  "filters": [
    "Все",
    "Огонь",
    "Вода",
    "Ветер",
    "Земля"
  ]
}